Metadata-Version: 2.4
Name: iflow-mcp_berlinbra_bluesky_mcp
Version: 0.1.0
Author-email: berlinbra <BMBpsn@gmail.com>
License-File: LICENSE
Requires-Python: >=3.11
Requires-Dist: atproto>=0.0.47
Requires-Dist: mcp>=0.1.0
Requires-Dist: pydantic>=2.0.0
